Metadata-Version: 1.1
Name: dwcv
Version: 0.0.1.1
Summary: OpenDWLab Computer Vision Foundation
Home-page: https://github.com/opendwlab/dwcv
Author: dwcv
Author-email: opendwlab@gmail.com
License: UNKNOWN
Keywords: computer vision
Platform: UNKNOWN
Classifier: Development Status :: 4 - Beta
Classifier: License :: OSI Approved :: Apache Software License
Classifier: Operating System :: OS Independent
Classifier: Programming Language :: Python :: 3
Classifier: Programming Language :: Python :: 3.6
Classifier: Programming Language :: Python :: 3.7
Classifier: Programming Language :: Python :: 3.8
Classifier: Topic :: Utilities
